{
    "cards": [
        {
            "id": 1,
            "title": "test 1",
            "short_description": "test 1",
            "description": "test 1 test 1 test 1 test 1",
            "status": false,
            "favorite": false,
            "date": "28/2/2026"
        },{
            "id": 2,
            "title": "test 2",
            "short_description": "test 2",
            "description": "test 2 test 2 test 2 test 2",
            "status": true,
            "favorite": false,
            "date": "28/2/2026"
        },{
            "id": 3,
            "title": "test 3",
            "short_description": "test 3",
            "description": "test 3 test 3 test 3 test 3",
            "status": true,
            "favorite": false,
            "date": "28/2/2026"
        },{
            "id": 4,
            "title": "test 4",
            "short_description": "test 4",
            "description": "test 4 test 4 test 4 test 4",
            "status": false,
            "favorite": false,
            "date": "28/2/2026"
        },{
            "id": 5,
            "title": "test 5",
            "short_description": "test 5",
            "description": "test 5 test 5 test 5 test 5",
            "status": false,
            "favorite": false,
            "date": "28/2/2026"
        },{
            "id": 6,
            "title": "test 6",
            "short_description": "test 6",
            "description": "test 6 test 6 test 6 test 6",
            "status": true,
            "favorite": false,
            "date": "28/2/2026"
        }
    ] 
}